{
  "entities": [ {
    "value": "\\d{5}",
    "synonyms": [ "\\d{5}" ],
    "languageCode": "en"
  }, {
    "value": "\\d \\d \\d \\d \\d",
    "synonyms": [ "\\d \\d \\d \\d \\d" ],
    "languageCode": "en"
  }, {
    "value": "(zero|one|two|three|four|five|six|seven|eight|nine) (zero|one|two|three|four|five|six|seven|eight|nine) (zero|one|two|three|four|five|six|seven|eight|nine) (zero|one|two|three|four|five|six|seven|eight|nine) (zero|one|two|three|four|five|six|seven|eight|nine)",
    "synonyms": [ "(zero|one|two|three|four|five|six|seven|eight|nine) (zero|one|two|three|four|five|six|seven|eight|nine) (zero|one|two|three|four|five|six|seven|eight|nine) (zero|one|two|three|four|five|six|seven|eight|nine) (zero|one|two|three|four|five|six|seven|eight|nine)" ],
    "languageCode": "en"
  } ]
}
